{
	"parent": "item/generated",
	"textures": {
		"layer0": "minecraft:item/leather_horse_armor"
	},
	"overrides": [
		{
			"predicate": {
				"custom_model_data": 1
			},
			"model": "item/animated_java_empty"
		},
		{
			"predicate": {
				"custom_model_data": 2
			},
			"model": "animated_java:item/original_lv/tread"
		},
		{
			"predicate": {
				"custom_model_data": 3
			},
			"model": "animated_java:item/original_lv/turret"
		},
		{
			"predicate": {
				"custom_model_data": 4
			},
			"model": "animated_java:item/original_mv/turret"
		},
		{
			"predicate": {
				"custom_model_data": 5
			},
			"model": "animated_java:item/original_mv/tread"
		},
		{
			"predicate": {
				"custom_model_data": 6
			},
			"model": "animated_java:item/original_vehicle_mv/turret"
		},
		{
			"predicate": {
				"custom_model_data": 7
			},
			"model": "animated_java:item/original_vehicle_mv/tread"
		},
		{
			"predicate": {
				"custom_model_data": 8
			},
			"model": "animated_java:item/original_vehicle_lv/tread"
		},
		{
			"predicate": {
				"custom_model_data": 9
			},
			"model": "animated_java:item/original_vehicle_lv/turret"
		}
	],
	"animated_java": {
		"rigs": {
			"original_lv": {
				"used_ids": [
					2,
					3
				]
			},
			"original_mv": {
				"used_ids": [
					4,
					5
				]
			},
			"original_vehicle_mv": {
				"used_ids": [
					6,
					7
				]
			},
			"original_vehicle_lv": {
				"used_ids": [
					8,
					9
				]
			}
		}
	}
}